detect_secrets/__init__.py
detect_secrets/__main__.py
detect_secrets/__version__.py
detect_secrets/constants.py
detect_secrets/custom_types.py
detect_secrets/exceptions.py
detect_secrets/main.py
detect_secrets/pre_commit_hook.py
detect_secrets/py.typed
detect_secrets/settings.py
detect_secrets/audit/__init__.py
detect_secrets/audit/analytics.py
detect_secrets/audit/audit.py
detect_secrets/audit/common.py
detect_secrets/audit/compare.py
detect_secrets/audit/io.py
detect_secrets/audit/iterator.py
detect_secrets/audit/report.py
detect_secrets/core/__init__.py
detect_secrets/core/baseline.py
detect_secrets/core/log.py
detect_secrets/core/potential_secret.py
detect_secrets/core/scan.py
detect_secrets/core/secrets_collection.py
detect_secrets/core/plugins/__init__.py
detect_secrets/core/plugins/initialize.py
detect_secrets/core/plugins/util.py
detect_secrets/core/upgrades/__init__.py
detect_secrets/core/upgrades/v0_12.py
detect_secrets/core/upgrades/v1_0.py
detect_secrets/core/upgrades/v1_1.py
detect_secrets/core/usage/__init__.py
detect_secrets/core/usage/audit.py
detect_secrets/core/usage/baseline.py
detect_secrets/core/usage/common.py
detect_secrets/core/usage/filters.py
detect_secrets/core/usage/plugins.py
detect_secrets/core/usage/scan.py
detect_secrets/filters/__init__.py
detect_secrets/filters/allowlist.py
detect_secrets/filters/common.py
detect_secrets/filters/heuristic.py
detect_secrets/filters/regex.py
detect_secrets/filters/util.py
detect_secrets/filters/wordlist.py
detect_secrets/filters/gibberish/__init__.py
detect_secrets/filters/gibberish/rfc.model
detect_secrets/plugins/__init__.py
detect_secrets/plugins/artifactory.py
detect_secrets/plugins/aws.py
detect_secrets/plugins/azure_storage_key.py
detect_secrets/plugins/base.py
detect_secrets/plugins/basic_auth.py
detect_secrets/plugins/cloudant.py
detect_secrets/plugins/discord.py
detect_secrets/plugins/github_token.py
detect_secrets/plugins/high_entropy_strings.py
detect_secrets/plugins/ibm_cloud_iam.py
bc_detect_secrets-1.5.45.dist-info/LICENSE
bc_detect_secrets-1.5.45.dist-info/METADATA
bc_detect_secrets-1.5.45.dist-info/WHEEL
bc_detect_secrets-1.5.45.dist-info/entry_points.txt
bc_detect_secrets-1.5.45.dist-info/top_level.txt
bc_detect_secrets-1.5.45.dist-info/RECORD
