Metadata-Version: 2.1
Name: bc-detect-secrets
Version: 1.5.45
Summary: Tool for detecting secrets in the codebase
Home-page: https://github.com/bridgecrewio/detect-secrets
Author: bridgecrew
Author-email: meet@bridgecrew.io
License: Apache License 2.0
Keywords: secret-management,pre-commit,security,entropy-checks
Classifier: Programming Language :: Python :: 3 :: Only
Classifier: Programming Language :: Python :: 3.8
Classifier: Programming Language :: Python :: 3.9
Classifier: Programming Language :: Python :: 3.10
Classifier: Programming Language :: Python :: 3.11
Classifier: Programming Language :: Python :: 3.12
Classifier: Programming Language :: Python :: 3.13
Classifier: License :: OSI Approved :: Apache Software License
Classifier: Intended Audience :: Developers
Classifier: Topic :: Software Development
Classifier: Topic :: Utilities
Classifier: Environment :: Console
Classifier: Operating System :: OS Independent
Classifier: Development Status :: 5 - Production/Stable
Classifier: Typing :: Typed
Requires-Python: >=3.8
License-File: LICENSE
Requires-Dist: pyyaml
Requires-Dist: requests
Requires-Dist: unidiff
Provides-Extra: word-list
Requires-Dist: pyahocorasick; extra == "word-list"
Provides-Extra: gibberish
Requires-Dist: gibberish-detector; extra == "gibberish"
